omnisolver/common/__init__.py
omnisolver/common/cmd.py
omnisolver/common/plugin.py
omnisolver/common/py.typed
omnisolver/common/serialization.py
omnisolver/random/__init__.py
omnisolver/random/py.typed
omnisolver/random/random.yml
omnisolver/random/sampler.py
omnisolver-0.0.4.dist-info/LICENSE
omnisolver-0.0.4.dist-info/METADATA
omnisolver-0.0.4.dist-info/WHEEL
omnisolver-0.0.4.dist-info/entry_points.txt
omnisolver-0.0.4.dist-info/RECORD
