Metadata-Version: 2.3
Name: omnisolver
Version: 0.0.4
Summary: Extensible framework for creating and running Binary Quadratic Model solvers and samplers.
License: Apache-2.0
Author: Konrad Jałowiecki
Author-email: dexter2206@gmail.com
Requires-Python: >=3.9,<4.0
Classifier: Intended Audience :: Other Audience
Classifier: Intended Audience :: Science/Research
Classifier: License :: OSI Approved :: Apache Software License
Classifier: Programming Language :: Python :: 3
Classifier: Programming Language :: Python :: 3.9
Classifier: Programming Language :: Python :: 3.10
Classifier: Programming Language :: Python :: 3.11
Classifier: Programming Language :: Python :: 3.12
Classifier: Programming Language :: Python :: 3.13
Classifier: Topic :: Scientific/Engineering :: Physics
Requires-Dist: dimod (>=0.12,<0.13)
Requires-Dist: numpy (>=2.0.0,<3.0.0)
Requires-Dist: pandas (>=2.2.2,<3.0.0)
Requires-Dist: pyyaml (>=6.0.1,<7.0.0)
